girder_hashsum_download/__init__.py
girder_hashsum_download/settings.py
girder_hashsum_download/web_client/dist/girder-plugin-hashsum-download.umd.cjs
girder_hashsum_download/web_client/dist/style.css
girder_hashsum_download-5.0.0a14.dev27.dist-info/METADATA
girder_hashsum_download-5.0.0a14.dev27.dist-info/WHEEL
girder_hashsum_download-5.0.0a14.dev27.dist-info/entry_points.txt
girder_hashsum_download-5.0.0a14.dev27.dist-info/top_level.txt
girder_hashsum_download-5.0.0a14.dev27.dist-info/RECORD
