Metadata-Version: 2.4
Name: girder-hashsum-download
Version: 5.0.0a14.dev27
Summary: Allows download of a file by its hashsum.
Home-page: http://girder.readthedocs.io/en/latest/plugins.html#hashsum-download
Author: Kitware, Inc.
Author-email: kitware@kitware.com
License: Apache 2.0
Classifier: Development Status :: 5 - Production/Stable
Classifier: Environment :: Web Environment
Classifier: Operating System :: OS Independent
Classifier: Programming Language :: Python
Classifier: Programming Language :: Python :: 3
Requires-Python: >=3.10
Requires-Dist: girder>=3
Dynamic: author
Dynamic: author-email
Dynamic: classifier
Dynamic: home-page
Dynamic: license
Dynamic: requires-dist
Dynamic: requires-python
Dynamic: summary
